abeci/__init__.py
abeci/arguments.py
abeci/cache.py
abeci/config.py
abeci/defaults.py
abeci/fileHandler.py
abeci/flushHandler.py
abeci/listMaps.py
abeci/listPatterns.py
abeci/logHandler.py
abeci/logging.py
abeci/maps.py
abeci/pangrams.py
abeci/patterns.py
abeci/readFromCache.py
abeci/readWordRecords.py
abeci/recounter.py
abeci/savePangrams.py
abeci/toPangrams.py
abeci/typo/__init__.py
abeci/typo/loadTypos.py
abeci/typo/data/aspell.dat.txt
abeci/typo/data/holbrook-tagged.dat.txt
abeci/typo/data/missp.dat.txt
abeci/typo/data/wikipedia.dat.txt
abeci-1.0.5.dist-info/LICENSE
abeci-1.0.5.dist-info/METADATA
abeci-1.0.5.dist-info/WHEEL
abeci-1.0.5.dist-info/entry_points.txt
abeci-1.0.5.dist-info/top_level.txt
abeci-1.0.5.dist-info/RECORD
