Metadata-Version: 2.1
Name: abeci
Version: 1.0.5
Summary: Find perfect pangrams
Home-page: https://github.com/tvquizphd/abeci
Author: TVQuizPhD
Author-email: tvquizphd@email.com
License: UNKNOWN
Platform: UNKNOWN
Classifier: Programming Language :: Python :: 3
Classifier: License :: OSI Approved :: MIT License
Classifier: Operating System :: OS Independent
Classifier: Natural Language :: English
Classifier: Intended Audience :: Science/Research
Classifier: Topic :: Text Processing :: Linguistic
Classifier: Topic :: Scientific/Engineering :: Information Analysis
Classifier: Topic :: Software Development :: Libraries :: Python Modules
License-File: LICENSE
Requires-Dist: abeci
